pycargo/__init__.py
pycargo/containers.py
pycargo/exceptions.py
pycargo/fields.py
pycargo/spreadsheet.py
pycargo/styles.py
pycargo/types.py
pycargo/utils.py
pycargo/validate.py
pycargo/tests/__init__.py
pycargo/tests/test_containers.py
pycargo/tests/test_validate.py
pycargo-2.1.0.dist-info/LICENSE
pycargo-2.1.0.dist-info/METADATA
pycargo-2.1.0.dist-info/WHEEL
pycargo-2.1.0.dist-info/top_level.txt
pycargo-2.1.0.dist-info/RECORD
