Metadata-Version: 2.1
Name: pycargo
Version: 2.1.0
Summary: Pycargo is a utility to work with loading and exporting data from excel
Home-page: https://gitlab.com/taranjeet.singh.3312/pycargo
Author: Taranjeet Singh
Author-email: taranjeet.singh.3312@gmail.com
License: UNKNOWN
Platform: UNKNOWN
Classifier: Programming Language :: Python :: 3
Classifier: License :: OSI Approved :: MIT License
Classifier: Operating System :: OS Independent
Requires-Python: >=3.6
Requires-Dist: validators (<2,>=0.18.2)
Requires-Dist: openpyxl (<4,>=3.0.5)
Requires-Dist: pandas (<2,>=1.2.0)
